log_request_id/__init__.py
log_request_id/filters.py
log_request_id/middleware.py
log_request_id/models.py
log_request_id/session.py
log_request_id/tests.py
log_request_id/__pycache__/__init__.cpython-38.pyc
log_request_id/__pycache__/filters.cpython-38.pyc
log_request_id/__pycache__/middleware.cpython-38.pyc
log_request_id/__pycache__/models.cpython-38.pyc
log_request_id/__pycache__/session.cpython-38.pyc
log_request_id/__pycache__/tests.cpython-38.pyc
nhst_log_request_id/__init__.py
nhst_log_request_id/filters.py
nhst_log_request_id/middleware.py
nhst_log_request_id/models.py
nhst_log_request_id/session.py
nhst_log_request_id/tests.py
nhst_log_request_id/__pycache__/__init__.cpython-38.pyc
nhst_log_request_id/__pycache__/filters.cpython-38.pyc
nhst_log_request_id/__pycache__/middleware.cpython-38.pyc
nhst_log_request_id/__pycache__/models.cpython-38.pyc
nhst_log_request_id/__pycache__/session.cpython-38.pyc
nhst_log_request_id/__pycache__/tests.cpython-38.pyc
nhst_log_request_id-1.0.2.dist-info/LICENSE
nhst_log_request_id-1.0.2.dist-info/METADATA
nhst_log_request_id-1.0.2.dist-info/WHEEL
nhst_log_request_id-1.0.2.dist-info/top_level.txt
nhst_log_request_id-1.0.2.dist-info/RECORD
