Metadata-Version: 2.1
Name: nhst-log-request-id
Version: 1.0.2
Summary: Django middleware and log filter to attach a unique ID to every log message generated as part of a request
Home-page: https://github.com/DreamRunnerMoshi/django-log-request-id/
Author: Moshi
Author-email: moshiur.rahman@nhst.com
License: BSD
Platform: UNKNOWN
Requires-Dist: django (>=1.8)
